{
  "nodes": [
    {
      "id": 7,
      "label": "B",
      "group": "Fire",
      "type": "basic",
      "x": -1385,
      "y": -37,
      "fixed": true,
      "shape": "dot",
      "color": "#7dd3fc",
      "size": 14
    },
    {
      "id": 8,
      "label": "B",
      "group": "Fire",
      "type": "basic",
      "x": -1072,
      "y": -160,
      "fixed": true,
      "shape": "dot",
      "color": "#7dd3fc",
      "size": 14
    },
    {
      "id": 9,
      "label": "B",
      "group": "Fire",
      "type": "basic",
      "x": -807,
      "y": -196,
      "fixed": false,
      "shape": "dot",
      "color": "#7dd3fc",
      "size": 14
    },
    {
      "id": 10,
      "label": "B",
      "group": "Fire",
      "type": "basic",
      "x": -511,
      "y": -216,
      "fixed": false,
      "shape": "dot",
      "color": "#7dd3fc",
      "size": 14
    },
    {
      "id": 11,
      "label": "B",
      "group": "Fire",
      "type": "basic",
      "x": -367,
      "y": -220,
      "fixed": false,
      "shape": "dot",
      "color": "#7dd3fc",
      "size": 14
    },
    {
      "id": 12,
      "label": "B",
      "group": "Fire",
      "type": "basic",
      "x": -376,
      "y": 462,
      "fixed": true,
      "shape": "dot",
      "color": "#7dd3fc",
      "size": 14
    },
    {
      "id": 13,
      "label": "B",
      "group": "Fire",
      "type": "basic",
      "x": -227,
      "y": 302,
      "fixed": false,
      "shape": "dot",
      "color": "#7dd3fc",
      "size": 14
    },
    {
      "id": 15,
      "label": "B",
      "group": "Fire",
      "type": "basic",
      "x": 285,
      "y": 460,
      "fixed": false,
      "shape": "dot",
      "color": "#7dd3fc",
      "size": 14
    },
    {
      "id": 16,
      "label": "B",
      "group": "Fire",
      "type": "basic",
      "x": 598,
      "y": 15,
      "fixed": false,
      "shape": "dot",
      "color": "#7dd3fc",
      "size": 14
    },
    {
      "id": 17,
      "label": "B",
      "group": "Fire",
      "type": "basic",
      "x": 254,
      "y": 255,
      "fixed": false,
      "shape": "dot",
      "color": "#7dd3fc",
      "size": 14
    },
    {
      "id": 24,
      "label": "B",
      "group": "Fire",
      "type": "basic",
      "x": -1300,
      "y": 220,
      "fixed": true,
      "shape": "dot",
      "color": "#7dd3fc",
      "size": 14
    },
    {
      "id": 25,
      "label": "B",
      "group": "Fire",
      "type": "basic",
      "x": -1124,
      "y": 159,
      "fixed": true,
      "shape": "dot",
      "color": "#7dd3fc",
      "size": 14
    },
    {
      "id": 26,
      "label": "B",
      "group": "Fire",
      "type": "basic",
      "x": -986,
      "y": 281,
      "fixed": true,
      "shape": "dot",
      "color": "#7dd3fc",
      "size": 14
    },
    {
      "id": 27,
      "label": "B",
      "group": "Fire",
      "type": "basic",
      "x": -840,
      "y": -71,
      "fixed": true,
      "shape": "dot",
      "color": "#7dd3fc",
      "size": 14
    },
    {
      "id": 28,
      "label": "Notable",
      "group": "Fire",
      "type": "notable",
      "x": -1092,
      "y": 62,
      "fixed": true,
      "shape": "dot",
      "color": "#7dd3fc",
      "size": 14
    },
    {
      "id": 29,
      "label": "B",
      "group": "Fire",
      "type": "basic",
      "x": -642,
      "y": -70,
      "fixed": true,
      "shape": "dot",
      "color": "#7dd3fc",
      "size": 14
    },
    {
      "id": 30,
      "label": "B",
      "group": "Fire",
      "type": "basic",
      "x": -803,
      "y": 291,
      "fixed": true,
      "shape": "dot",
      "color": "#7dd3fc",
      "size": 14
    },
    {
      "id": 31,
      "label": "B",
      "group": "Fire",
      "type": "basic",
      "x": -469,
      "y": 329,
      "fixed": true,
      "shape": "dot",
      "color": "#7dd3fc",
      "size": 14
    },
    {
      "id": 32,
      "label": "B",
      "group": "Fire",
      "type": "basic",
      "x": -619,
      "y": 209,
      "fixed": true,
      "shape": "dot",
      "color": "#7dd3fc",
      "size": 14
    },
    {
      "id": 33,
      "label": "Notable",
      "group": "Fire",
      "type": "notable",
      "x": -568,
      "y": 71,
      "fixed": true,
      "shape": "dot",
      "color": "#7dd3fc",
      "size": 14
    },
    {
      "id": 34,
      "label": "B",
      "group": "Fire",
      "type": "basic",
      "x": -290,
      "y": 14,
      "fixed": false,
      "shape": "dot",
      "color": "#7dd3fc",
      "size": 14
    },
    {
      "id": 35,
      "label": "B",
      "group": "Fire",
      "type": "basic",
      "x": -212,
      "y": -219,
      "fixed": false,
      "shape": "dot",
      "color": "#7dd3fc",
      "size": 14
    },
    {
      "id": 36,
      "label": "B",
      "group": "Fire",
      "type": "basic",
      "x": 37,
      "y": -194,
      "fixed": false,
      "shape": "dot",
      "color": "#7dd3fc",
      "size": 14
    },
    {
      "id": 37,
      "label": "B",
      "group": "Fire",
      "type": "basic",
      "x": 317,
      "y": -123,
      "fixed": false,
      "shape": "dot",
      "color": "#7dd3fc",
      "size": 14
    },
    {
      "id": 38,
      "label": "Notable",
      "group": "Fire",
      "type": "notable",
      "x": 71,
      "y": 82,
      "fixed": false,
      "shape": "dot",
      "color": "#7dd3fc",
      "size": 14
    },
    {
      "id": 39,
      "label": "B",
      "group": "Fire",
      "type": "basic",
      "x": 451,
      "y": -74,
      "fixed": false,
      "shape": "dot",
      "color": "#7dd3fc",
      "size": 14
    },
    {
      "id": 40,
      "label": "B",
      "group": "Fire",
      "type": "basic",
      "x": 508,
      "y": -219,
      "fixed": false,
      "shape": "dot",
      "color": "#7dd3fc",
      "size": 14
    },
    {
      "id": 41,
      "label": "B",
      "group": "Fire",
      "type": "basic",
      "x": 733,
      "y": -168,
      "fixed": false,
      "shape": "dot",
      "color": "#7dd3fc",
      "size": 14
    },
    {
      "id": 42,
      "label": "B",
      "group": "Fire",
      "type": "basic",
      "x": 777,
      "y": -247,
      "fixed": false,
      "shape": "dot",
      "color": "#7dd3fc",
      "size": 14
    },
    {
      "id": 43,
      "label": "Notable",
      "group": "Fire",
      "type": "notable",
      "x": 602,
      "y": -309,
      "fixed": false,
      "shape": "dot",
      "color": "#7dd3fc",
      "size": 14
    },
    {
      "id": 52,
      "label": "Notable",
      "group": "Fire",
      "type": "notable",
      "x": -195,
      "y": 87,
      "fixed": false,
      "shape": "dot",
      "color": "#7dd3fc",
      "size": 14
    },
    {
      "id": 53,
      "label": "B",
      "group": "Fire",
      "type": "basic",
      "x": 108,
      "y": 281,
      "fixed": false,
      "shape": "dot",
      "color": "#7dd3fc",
      "size": 14
    },
    {
      "id": 55,
      "label": "B",
      "group": "Fire",
      "type": "basic",
      "x": -403.77060782862645,
      "y": -913.809710253139,
      "fixed": false,
      "shape": "dot",
      "color": "#7dd3fc",
      "size": 14
    },
    {
      "id": 56,
      "label": "B",
      "group": "Fire",
      "type": "basic",
      "x": -140.7494831631405,
      "y": -704.2437588686098,
      "fixed": false,
      "shape": "dot",
      "color": "#7dd3fc",
      "size": 14
    },
    {
      "id": 57,
      "label": "B",
      "group": "Fire",
      "type": "basic",
      "x": 22.927431373099324,
      "y": -492.7470268657335,
      "fixed": false,
      "shape": "dot",
      "color": "#7dd3fc",
      "size": 14
    },
    {
      "id": 58,
      "label": "B",
      "group": "Fire",
      "type": "basic",
      "x": 188.24793944878812,
      "y": -246.4035073455397,
      "fixed": false,
      "shape": "dot",
      "color": "#7dd3fc",
      "size": 14
    },
    {
      "id": 59,
      "label": "B",
      "group": "Fire",
      "type": "basic",
      "x": 263.7120410639259,
      "y": -123.69584920058054,
      "fixed": false,
      "shape": "dot",
      "color": "#7dd3fc",
      "size": 14
    },
    {
      "id": 60,
      "label": "B",
      "group": "Fire",
      "type": "basic",
      "x": -331.4172843170613,
      "y": 209.5099221653596,
      "fixed": false,
      "shape": "dot",
      "color": "#7dd3fc",
      "size": 14
    },
    {
      "id": 61,
      "label": "B",
      "group": "Fire",
      "type": "basic",
      "x": -118.35321971155105,
      "y": 258.5477073292409,
      "fixed": false,
      "shape": "dot",
      "color": "#7dd3fc",
      "size": 14
    },
    {
      "id": 62,
      "label": "B",
      "group": "Fire",
      "type": "basic",
      "x": 0.8147664905076795,
      "y": 780.9527140668735,
      "fixed": false,
      "shape": "dot",
      "color": "#7dd3fc",
      "size": 14
    },
    {
      "id": 63,
      "label": "B",
      "group": "Fire",
      "type": "basic",
      "x": 542.696071174583,
      "y": 829.5186654514027,
      "fixed": false,
      "shape": "dot",
      "color": "#7dd3fc",
      "size": 14
    },
    {
      "id": 64,
      "label": "B",
      "group": "Fire",
      "type": "basic",
      "x": 162.84997426631762,
      "y": 651.6059265495559,
      "fixed": false,
      "shape": "dot",
      "color": "#7dd3fc",
      "size": 14
    },
    {
      "id": 65,
      "label": "B",
      "group": "Fire",
      "type": "basic",
      "x": -583.8391366012272,
      "y": -711.6975509314617,
      "fixed": false,
      "shape": "dot",
      "color": "#7dd3fc",
      "size": 14
    },
    {
      "id": 66,
      "label": "B",
      "group": "Fire",
      "type": "basic",
      "x": -443.0115869703764,
      "y": -589.7770798654005,
      "fixed": false,
      "shape": "dot",
      "color": "#7dd3fc",
      "size": 14
    },
    {
      "id": 67,
      "label": "B",
      "group": "Fire",
      "type": "basic",
      "x": -479.66668623207795,
      "y": -409.265574143148,
      "fixed": false,
      "shape": "dot",
      "color": "#7dd3fc",
      "size": 14
    },
    {
      "id": 68,
      "label": "B",
      "group": "Fire",
      "type": "basic",
      "x": -101.8257440999555,
      "y": -458.82586519062,
      "fixed": false,
      "shape": "dot",
      "color": "#7dd3fc",
      "size": 14
    },
    {
      "id": 69,
      "label": "Notable",
      "group": "Fire",
      "type": "notable",
      "x": -343.0071228032859,
      "y": -610.5642669442984,
      "fixed": false,
      "shape": "dot",
      "color": "#7dd3fc",
      "size": 14
    },
    {
      "id": 70,
      "label": "B",
      "group": "Fire",
      "type": "basic",
      "x": -3.6917695037399056,
      "y": -286.85283524130114,
      "fixed": false,
      "shape": "dot",
      "color": "#7dd3fc",
      "size": 14
    },
    {
      "id": 71,
      "label": "B",
      "group": "Fire",
      "type": "basic",
      "x": -396.82694026992226,
      "y": -245.78292525059575,
      "fixed": false,
      "shape": "dot",
      "color": "#7dd3fc",
      "size": 14
    },
    {
      "id": 72,
      "label": "B",
      "group": "Fire",
      "type": "basic",
      "x": -262.7359056137309,
      "y": 62.46955961340677,
      "fixed": false,
      "shape": "dot",
      "color": "#7dd3fc",
      "size": 14
    },
    {
      "id": 73,
      "label": "B",
      "group": "Fire",
      "type": "basic",
      "x": -233.81285715959828,
      "y": -127.43425095425903,
      "fixed": false,
      "shape": "dot",
      "color": "#7dd3fc",
      "size": 14
    },
    {
      "id": 74,
      "label": "Notable",
      "group": "Fire",
      "type": "notable",
      "x": -88.80135143734576,
      "y": -152.26695536125268,
      "fixed": false,
      "shape": "dot",
      "color": "#7dd3fc",
      "size": 14
    },
    {
      "id": 75,
      "label": "B",
      "group": "Fire",
      "type": "basic",
      "x": 99.56209657836729,
      "y": 59.98810689082124,
      "fixed": false,
      "shape": "dot",
      "color": "#7dd3fc",
      "size": 14
    },
    {
      "id": 76,
      "label": "B",
      "group": "Fire",
      "type": "basic",
      "x": 340.34601566014146,
      "y": 11.038088386007445,
      "fixed": false,
      "shape": "dot",
      "color": "#7dd3fc",
      "size": 14
    },
    {
      "id": 77,
      "label": "B",
      "group": "Fire",
      "type": "basic",
      "x": 443.19538056553057,
      "y": 239.17841392833265,
      "fixed": false,
      "shape": "dot",
      "color": "#7dd3fc",
      "size": 14
    },
    {
      "id": 78,
      "label": "B",
      "group": "Fire",
      "type": "basic",
      "x": 521.7075768968355,
      "y": 517.1655269879755,
      "fixed": false,
      "shape": "dot",
      "color": "#7dd3fc",
      "size": 14
    },
    {
      "id": 79,
      "label": "Notable",
      "group": "Fire",
      "type": "notable",
      "x": 221.17236912102553,
      "y": 406.6232776570036,
      "fixed": false,
      "shape": "dot",
      "color": "#7dd3fc",
      "size": 14
    },
    {
      "id": 80,
      "label": "B",
      "group": "Fire",
      "type": "basic",
      "x": 546.272332111398,
      "y": 657.7129310950902,
      "fixed": false,
      "shape": "dot",
      "color": "#7dd3fc",
      "size": 14
    },
    {
      "id": 81,
      "label": "B",
      "group": "Fire",
      "type": "basic",
      "x": 700.3460156601416,
      "y": 634.5763791108031,
      "fixed": false,
      "shape": "dot",
      "color": "#7dd3fc",
      "size": 14
    },
    {
      "id": 82,
      "label": "B",
      "group": "Fire",
      "type": "basic",
      "x": 768.6787200671353,
      "y": 854.9320949623019,
      "fixed": false,
      "shape": "dot",
      "color": "#7dd3fc",
      "size": 14
    },
    {
      "id": 83,
      "label": "B",
      "group": "Fire",
      "type": "basic",
      "x": 859.0947269661059,
      "y": 853.5372127288172,
      "fixed": false,
      "shape": "dot",
      "color": "#7dd3fc",
      "size": 14
    },
    {
      "id": 84,
      "label": "Notable",
      "group": "Fire",
      "type": "notable",
      "x": 825.288302000741,
      "y": 670.9827670665404,
      "fixed": false,
      "shape": "dot",
      "color": "#7dd3fc",
      "size": 14
    },
    {
      "id": 86,
      "label": "Notable",
      "group": "Fire",
      "type": "notable",
      "x": 83.84224210210326,
      "y": 178.76052025034292,
      "fixed": false,
      "shape": "dot",
      "color": "#7dd3fc",
      "size": 14
    },
    {
      "id": 87,
      "label": "B",
      "group": "Fire",
      "type": "basic",
      "x": 67.33331376792219,
      "y": 538.1662175970279,
      "fixed": false,
      "shape": "dot",
      "color": "#7dd3fc",
      "size": 14
    },
    {
      "id": 89,
      "label": "B",
      "group": "Fire",
      "type": "basic",
      "x": 626.8176274654911,
      "y": -831.2214749590216,
      "fixed": false,
      "shape": "dot",
      "color": "#7dd3fc",
      "size": 14
    },
    {
      "id": 90,
      "label": "B",
      "group": "Fire",
      "type": "basic",
      "x": 576.8387521309771,
      "y": -498.65552357449224,
      "fixed": false,
      "shape": "dot",
      "color": "#7dd3fc",
      "size": 14
    },
    {
      "id": 91,
      "label": "B",
      "group": "Fire",
      "type": "basic",
      "x": 475.515666667217,
      "y": -251.15879157161604,
      "fixed": false,
      "shape": "dot",
      "color": "#7dd3fc",
      "size": 14
    },
    {
      "id": 92,
      "label": "B",
      "group": "Fire",
      "type": "basic",
      "x": 344.83617474290577,
      "y": 15.184727948577859,
      "fixed": false,
      "shape": "dot",
      "color": "#7dd3fc",
      "size": 14
    },
    {
      "id": 93,
      "label": "B",
      "group": "Fire",
      "type": "basic",
      "x": 276.3002763580436,
      "y": 141.89238609353703,
      "fixed": false,
      "shape": "dot",
      "color": "#7dd3fc",
      "size": 14
    },
    {
      "id": 94,
      "label": "B",
      "group": "Fire",
      "type": "basic",
      "x": -309.82904902294365,
      "y": -206.90184254052286,
      "fixed": false,
      "shape": "dot",
      "color": "#7dd3fc",
      "size": 14
    },
    {
      "id": 95,
      "label": "B",
      "group": "Fire",
      "type": "basic",
      "x": -245.76498441743337,
      "y": 2.135942623358531,
      "fixed": false,
      "shape": "dot",
      "color": "#7dd3fc",
      "size": 14
    },
    {
      "id": 96,
      "label": "B",
      "group": "Fire",
      "type": "basic",
      "x": -638.5969982153747,
      "y": 366.5409493609912,
      "fixed": false,
      "shape": "dot",
      "color": "#7dd3fc",
      "size": 14
    },
    {
      "id": 97,
      "label": "B",
      "group": "Fire",
      "type": "basic",
      "x": -409.71569353129934,
      "y": 860.1069007455206,
      "fixed": false,
      "shape": "dot",
      "color": "#7dd3fc",
      "size": 14
    },
    {
      "id": 98,
      "label": "B",
      "group": "Fire",
      "type": "basic",
      "x": -445.56179043956473,
      "y": 442.1941618436736,
      "fixed": false,
      "shape": "dot",
      "color": "#7dd3fc",
      "size": 14
    },
    {
      "id": 99,
      "label": "B",
      "group": "Fire",
      "type": "basic",
      "x": 361.7490986928903,
      "y": -886.1093156373443,
      "fixed": false,
      "shape": "dot",
      "color": "#7dd3fc",
      "size": 14
    },
    {
      "id": 100,
      "label": "B",
      "group": "Fire",
      "type": "basic",
      "x": 326.5766483237411,
      "y": -703.188844571283,
      "fixed": false,
      "shape": "dot",
      "color": "#7dd3fc",
      "size": 14
    },
    {
      "id": 101,
      "label": "B",
      "group": "Fire",
      "type": "basic",
      "x": 151.92154906203962,
      "y": -644.6773388490305,
      "fixed": false,
      "shape": "dot",
      "color": "#7dd3fc",
      "size": 14
    },
    {
      "id": 102,
      "label": "B",
      "group": "Fire",
      "type": "basic",
      "x": 383.7624911941621,
      "y": -342.2376298965025,
      "fixed": false,
      "shape": "dot",
      "color": "#7dd3fc",
      "size": 14
    },
    {
      "id": 103,
      "label": "Notable",
      "group": "Fire",
      "type": "notable",
      "x": 394.58111249083163,
      "y": -626.976031650181,
      "fixed": false,
      "shape": "dot",
      "color": "#7dd3fc",
      "size": 14
    },
    {
      "id": 104,
      "label": "B",
      "group": "Fire",
      "type": "basic",
      "x": 283.8964657903777,
      "y": -171.2645999471836,
      "fixed": false,
      "shape": "dot",
      "color": "#7dd3fc",
      "size": 14
    },
    {
      "id": 105,
      "label": "B",
      "group": "Fire",
      "type": "basic",
      "x": 51.76129502419528,
      "y": -491.1946899564782,
      "fixed": false,
      "shape": "dot",
      "color": "#7dd3fc",
      "size": 14
    },
    {
      "id": 106,
      "label": "B",
      "group": "Fire",
      "type": "basic",
      "x": -148.1476703196133,
      "y": -220.9422050924756,
      "fixed": false,
      "shape": "dot",
      "color": "#7dd3fc",
      "size": 14
    },
    {
      "id": 107,
      "label": "B",
      "group": "Fire",
      "type": "basic",
      "x": 30.775378134519315,
      "y": -290.84601566014146,
      "fixed": false,
      "shape": "dot",
      "color": "#7dd3fc",
      "size": 14
    },
    {
      "id": 108,
      "label": "Notable",
      "group": "Fire",
      "type": "notable",
      "x": 124.78688385677191,
      "y": -177.67872006713515,
      "fixed": false,
      "shape": "dot",
      "color": "#7dd3fc",
      "size": 14
    },
    {
      "id": 109,
      "label": "B",
      "group": "Fire",
      "type": "basic",
      "x": 35.150331872484955,
      "y": 91.57634218493888,
      "fixed": false,
      "shape": "dot",
      "color": "#7dd3fc",
      "size": 14
    },
    {
      "id": 110,
      "label": "B",
      "group": "Fire",
      "type": "basic",
      "x": 197.93425095425917,
      "y": 275.62632368012504,
      "fixed": false,
      "shape": "dot",
      "color": "#7dd3fc",
      "size": 14
    },
    {
      "id": 111,
      "label": "B",
      "group": "Fire",
      "type": "basic",
      "x": 51.78361585964831,
      "y": 478.76664922245027,
      "fixed": false,
      "shape": "dot",
      "color": "#7dd3fc",
      "size": 14
    },
    {
      "id": 112,
      "label": "B",
      "group": "Fire",
      "type": "basic",
      "x": -149.70418780904686,
      "y": 685.7537622820932,
      "fixed": false,
      "shape": "dot",
      "color": "#7dd3fc",
      "size": 14
    },
    {
      "id": 113,
      "label": "Notable",
      "group": "Fire",
      "type": "notable",
      "x": -204.23939558485682,
      "y": 370.21151295112134,
      "fixed": false,
      "shape": "dot",
      "color": "#7dd3fc",
      "size": 14
    },
    {
      "id": 114,
      "label": "B",
      "group": "Fire",
      "type": "basic",
      "x": -259.13943259448433,
      "y": 777.301166389208,
      "fixed": false,
      "shape": "dot",
      "color": "#7dd3fc",
      "size": 14
    },
    {
      "id": 115,
      "label": "B",
      "group": "Fire",
      "type": "basic",
      "x": -162.0657490457407,
      "y": 899.1646144049209,
      "fixed": false,
      "shape": "dot",
      "color": "#7dd3fc",
      "size": 14
    },
    {
      "id": 116,
      "label": "B",
      "group": "Fire",
      "type": "basic",
      "x": -318.73304463874706,
      "y": 1068.5203302564198,
      "fixed": false,
      "shape": "dot",
      "color": "#7dd3fc",
      "size": 14
    },
    {
      "id": 117,
      "label": "B",
      "group": "Fire",
      "type": "basic",
      "x": -272.31703773977637,
      "y": 1146.125448022935,
      "fixed": false,
      "shape": "dot",
      "color": "#7dd3fc",
      "size": 14
    },
    {
      "id": 118,
      "label": "Notable",
      "group": "Fire",
      "type": "notable",
      "x": -131.1234627051412,
      "y": 1025.5710023606582,
      "fixed": false,
      "shape": "dot",
      "color": "#7dd3fc",
      "size": 14
    },
    {
      "id": 120,
      "label": "Notable",
      "group": "Fire",
      "type": "notable",
      "x": -75.56952260377906,
      "y": 137.34875554446052,
      "fixed": false,
      "shape": "dot",
      "color": "#7dd3fc",
      "size": 14
    },
    {
      "id": 121,
      "label": "B",
      "group": "Fire",
      "type": "basic",
      "x": -395.07845093796027,
      "y": 302.75445289114555,
      "fixed": false,
      "shape": "dot",
      "color": "#7dd3fc",
      "size": 14
    },
    {
      "id": 123,
      "label": "B",
      "group": "Fire",
      "type": "basic",
      "x": 1070.588235294118,
      "y": 102.58823529411717,
      "fixed": false,
      "shape": "dot",
      "color": "#7dd3fc",
      "size": 14
    },
    {
      "id": 124,
      "label": "B",
      "group": "Fire",
      "type": "basic",
      "x": 757.5882352941178,
      "y": 225.58823529411734,
      "fixed": false,
      "shape": "dot",
      "color": "#7dd3fc",
      "size": 14
    },
    {
      "id": 125,
      "label": "B",
      "group": "Fire",
      "type": "basic",
      "x": 492.58823529411785,
      "y": 261.58823529411745,
      "fixed": false,
      "shape": "dot",
      "color": "#7dd3fc",
      "size": 14
    },
    {
      "id": 126,
      "label": "B",
      "group": "Fire",
      "type": "basic",
      "x": 196.58823529411777,
      "y": 281.58823529411757,
      "fixed": false,
      "shape": "dot",
      "color": "#7dd3fc",
      "size": 14
    },
    {
      "id": 127,
      "label": "B",
      "group": "Fire",
      "type": "basic",
      "x": 52.58823529411782,
      "y": 285.5882352941177,
      "fixed": false,
      "shape": "dot",
      "color": "#7dd3fc",
      "size": 14
    },
    {
      "id": 128,
      "label": "B",
      "group": "Fire",
      "type": "basic",
      "x": 61.588235294117624,
      "y": -396.41176470588243,
      "fixed": false,
      "shape": "dot",
      "color": "#7dd3fc",
      "size": 14
    },
    {
      "id": 129,
      "label": "B",
      "group": "Fire",
      "type": "basic",
      "x": -87.41176470588233,
      "y": -236.41176470588232,
      "fixed": false,
      "shape": "dot",
      "color": "#7dd3fc",
      "size": 14
    },
    {
      "id": 130,
      "label": "B",
      "group": "Fire",
      "type": "basic",
      "x": -599.4117647058824,
      "y": -394.4117647058822,
      "fixed": false,
      "shape": "dot",
      "color": "#7dd3fc",
      "size": 14
    },
    {
      "id": 131,
      "label": "B",
      "group": "Fire",
      "type": "basic",
      "x": -912.4117647058824,
      "y": 50.58823529411802,
      "fixed": false,
      "shape": "dot",
      "color": "#7dd3fc",
      "size": 14
    },
    {
      "id": 132,
      "label": "B",
      "group": "Fire",
      "type": "basic",
      "x": -568.4117647058824,
      "y": -189.41176470588215,
      "fixed": false,
      "shape": "dot",
      "color": "#7dd3fc",
      "size": 14
    },
    {
      "id": 133,
      "label": "B",
      "group": "Fire",
      "type": "basic",
      "x": 985.5882352941178,
      "y": -154.41176470588283,
      "fixed": false,
      "shape": "dot",
      "color": "#7dd3fc",
      "size": 14
    },
    {
      "id": 134,
      "label": "B",
      "group": "Fire",
      "type": "basic",
      "x": 809.5882352941177,
      "y": -93.41176470588266,
      "fixed": false,
      "shape": "dot",
      "color": "#7dd3fc",
      "size": 14
    },
    {
      "id": 135,
      "label": "B",
      "group": "Fire",
      "type": "basic",
      "x": 671.5882352941178,
      "y": -215.41176470588272,
      "fixed": false,
      "shape": "dot",
      "color": "#7dd3fc",
      "size": 14
    },
    {
      "id": 136,
      "label": "B",
      "group": "Fire",
      "type": "basic",
      "x": 525.5882352941178,
      "y": 136.58823529411742,
      "fixed": false,
      "shape": "dot",
      "color": "#7dd3fc",
      "size": 14
    },
    {
      "id": 137,
      "label": "Notable",
      "group": "Fire",
      "type": "notable",
      "x": 777.5882352941176,
      "y": 3.5882352941172826,
      "fixed": false,
      "shape": "dot",
      "color": "#7dd3fc",
      "size": 14
    },
    {
      "id": 138,
      "label": "B",
      "group": "Fire",
      "type": "basic",
      "x": 327.58823529411774,
      "y": 135.5882352941175,
      "fixed": false,
      "shape": "dot",
      "color": "#7dd3fc",
      "size": 14
    },
    {
      "id": 139,
      "label": "B",
      "group": "Fire",
      "type": "basic",
      "x": 488.5882352941177,
      "y": -225.41176470588258,
      "fixed": false,
      "shape": "dot",
      "color": "#7dd3fc",
      "size": 14
    },
    {
      "id": 140,
      "label": "B",
      "group": "Fire",
      "type": "basic",
      "x": 154.5882352941176,
      "y": -263.41176470588243,
      "fixed": false,
      "shape": "dot",
      "color": "#7dd3fc",
      "size": 14
    },
    {
      "id": 141,
      "label": "B",
      "group": "Fire",
      "type": "basic",
      "x": 304.5882352941176,
      "y": -143.41176470588246,
      "fixed": false,
      "shape": "dot",
      "color": "#7dd3fc",
      "size": 14
    },
    {
      "id": 142,
      "label": "Notable",
      "group": "Fire",
      "type": "notable",
      "x": 253.58823529411774,
      "y": -5.411764705882462,
      "fixed": false,
      "shape": "dot",
      "color": "#7dd3fc",
      "size": 14
    },
    {
      "id": 143,
      "label": "B",
      "group": "Fire",
      "type": "basic",
      "x": -24.41176470588229,
      "y": 51.58823529411765,
      "fixed": false,
      "shape": "dot",
      "color": "#7dd3fc",
      "size": 14
    },
    {
      "id": 144,
      "label": "B",
      "group": "Fire",
      "type": "basic",
      "x": -102.41176470588223,
      "y": 284.5882352941176,
      "fixed": false,
      "shape": "dot",
      "color": "#7dd3fc",
      "size": 14
    },
    {
      "id": 145,
      "label": "B",
      "group": "Fire",
      "type": "basic",
      "x": -351.4117647058822,
      "y": 259.5882352941178,
      "fixed": false,
      "shape": "dot",
      "color": "#7dd3fc",
      "size": 14
    },
    {
      "id": 146,
      "label": "B",
      "group": "Fire",
      "type": "basic",
      "x": -631.4117647058822,
      "y": 188.58823529411782,
      "fixed": false,
      "shape": "dot",
      "color": "#7dd3fc",
      "size": 14
    },
    {
      "id": 147,
      "label": "Notable",
      "group": "Fire",
      "type": "notable",
      "x": -385.4117647058824,
      "y": -16.411764705882177,
      "fixed": false,
      "shape": "dot",
      "color": "#7dd3fc",
      "size": 14
    },
    {
      "id": 148,
      "label": "B",
      "group": "Fire",
      "type": "basic",
      "x": -765.4117647058822,
      "y": 139.58823529411782,
      "fixed": false,
      "shape": "dot",
      "color": "#7dd3fc",
      "size": 14
    },
    {
      "id": 149,
      "label": "B",
      "group": "Fire",
      "type": "basic",
      "x": -822.4117647058821,
      "y": 284.5882352941179,
      "fixed": false,
      "shape": "dot",
      "color": "#7dd3fc",
      "size": 14
    },
    {
      "id": 150,
      "label": "B",
      "group": "Fire",
      "type": "basic",
      "x": -1047.4117647058824,
      "y": 233.58823529411802,
      "fixed": false,
      "shape": "dot",
      "color": "#7dd3fc",
      "size": 14
    },
    {
      "id": 151,
      "label": "B",
      "group": "Fire",
      "type": "basic",
      "x": -1091.4117647058822,
      "y": 312.588235294118,
      "fixed": false,
      "shape": "dot",
      "color": "#7dd3fc",
      "size": 14
    },
    {
      "id": 152,
      "label": "Notable",
      "group": "Fire",
      "type": "notable",
      "x": -916.411764705882,
      "y": 374.58823529411785,
      "fixed": false,
      "shape": "dot",
      "color": "#7dd3fc",
      "size": 14
    },
    {
      "id": 154,
      "label": "Notable",
      "group": "Fire",
      "type": "notable",
      "x": -119.41176470588229,
      "y": -21.411764705882348,
      "fixed": false,
      "shape": "dot",
      "color": "#7dd3fc",
      "size": 14
    },
    {
      "id": 155,
      "label": "B",
      "group": "Fire",
      "type": "basic",
      "x": -422.4117647058825,
      "y": -215.4117647058823,
      "fixed": false,
      "shape": "dot",
      "color": "#7dd3fc",
      "size": 14
    },
    {
      "id": 157,
      "label": "B",
      "group": "Fire",
      "type": "basic",
      "x": 483.7706078286269,
      "y": 953.8097102531392,
      "fixed": false,
      "shape": "dot",
      "color": "#7dd3fc",
      "size": 14
    },
    {
      "id": 158,
      "label": "B",
      "group": "Fire",
      "type": "basic",
      "x": 220.74948316314064,
      "y": 744.2437588686098,
      "fixed": false,
      "shape": "dot",
      "color": "#7dd3fc",
      "size": 14
    },
    {
      "id": 159,
      "label": "B",
      "group": "Fire",
      "type": "basic",
      "x": 57.07256862690076,
      "y": 532.7470268657337,
      "fixed": false,
      "shape": "dot",
      "color": "#7dd3fc",
      "size": 14
    },
    {
      "id": 160,
      "label": "B",
      "group": "Fire",
      "type": "basic",
      "x": -108.2479394487882,
      "y": 286.4035073455398,
      "fixed": false,
      "shape": "dot",
      "color": "#7dd3fc",
      "size": 14
    },
    {
      "id": 161,
      "label": "B",
      "group": "Fire",
      "type": "basic",
      "x": -183.71204106392602,
      "y": 163.69584920058077,
      "fixed": false,
      "shape": "dot",
      "color": "#7dd3fc",
      "size": 14
    },
    {
      "id": 162,
      "label": "B",
      "group": "Fire",
      "type": "basic",
      "x": 411.4172843170611,
      "y": -169.5099221653596,
      "fixed": false,
      "shape": "dot",
      "color": "#7dd3fc",
      "size": 14
    },
    {
      "id": 163,
      "label": "B",
      "group": "Fire",
      "type": "basic",
      "x": 198.35321971155082,
      "y": -218.54770732924084,
      "fixed": false,
      "shape": "dot",
      "color": "#7dd3fc",
      "size": 14
    },
    {
      "id": 165,
      "label": "B",
      "group": "Fire",
      "type": "basic",
      "x": -462.69607117458344,
      "y": -789.5186654514025,
      "fixed": false,
      "shape": "dot",
      "color": "#7dd3fc",
      "size": 14
    },
    {
      "id": 166,
      "label": "B",
      "group": "Fire",
      "type": "basic",
      "x": -82.84997426631801,
      "y": -611.6059265495558,
      "fixed": false,
      "shape": "dot",
      "color": "#7dd3fc",
      "size": 14
    },
    {
      "id": 167,
      "label": "B",
      "group": "Fire",
      "type": "basic",
      "x": 663.8391366012276,
      "y": 751.6975509314617,
      "fixed": false,
      "shape": "dot",
      "color": "#7dd3fc",
      "size": 14
    },
    {
      "id": 168,
      "label": "B",
      "group": "Fire",
      "type": "basic",
      "x": 523.0115869703766,
      "y": 629.7770798654004,
      "fixed": false,
      "shape": "dot",
      "color": "#7dd3fc",
      "size": 14
    },
    {
      "id": 169,
      "label": "B",
      "group": "Fire",
      "type": "basic",
      "x": 559.6666862320781,
      "y": 449.265574143148,
      "fixed": false,
      "shape": "dot",
      "color": "#7dd3fc",
      "size": 14
    },
    {
      "id": 170,
      "label": "B",
      "group": "Fire",
      "type": "basic",
      "x": 181.82574409995556,
      "y": 498.82586519062,
      "fixed": false,
      "shape": "dot",
      "color": "#7dd3fc",
      "size": 14
    },
    {
      "id": 171,
      "label": "Notable",
      "group": "Fire",
      "type": "notable",
      "x": 423.00712280328594,
      "y": 650.5642669442983,
      "fixed": false,
      "shape": "dot",
      "color": "#7dd3fc",
      "size": 14
    },
    {
      "id": 172,
      "label": "B",
      "group": "Fire",
      "type": "basic",
      "x": 83.69176950373989,
      "y": 326.8528352413012,
      "fixed": false,
      "shape": "dot",
      "color": "#7dd3fc",
      "size": 14
    },
    {
      "id": 173,
      "label": "B",
      "group": "Fire",
      "type": "basic",
      "x": 476.8269402699223,
      "y": 285.78292525059567,
      "fixed": false,
      "shape": "dot",
      "color": "#7dd3fc",
      "size": 14
    },
    {
      "id": 174,
      "label": "B",
      "group": "Fire",
      "type": "basic",
      "x": 342.7359056137308,
      "y": -22.469559613406815,
      "fixed": false,
      "shape": "dot",
      "color": "#7dd3fc",
      "size": 14
    },
    {
      "id": 175,
      "label": "B",
      "group": "Fire",
      "type": "basic",
      "x": 313.81285715959814,
      "y": 167.434250954259,
      "fixed": false,
      "shape": "dot",
      "color": "#7dd3fc",
      "size": 14
    },
    {
      "id": 176,
      "label": "Notable",
      "group": "Fire",
      "type": "notable",
      "x": 168.80135143734572,
      "y": 192.26695536125274,
      "fixed": false,
      "shape": "dot",
      "color": "#7dd3fc",
      "size": 14
    },
    {
      "id": 177,
      "label": "B",
      "group": "Fire",
      "type": "basic",
      "x": -19.562096578367427,
      "y": -19.988106890821157,
      "fixed": false,
      "shape": "dot",
      "color": "#7dd3fc",
      "size": 14
    },
    {
      "id": 178,
      "label": "B",
      "group": "Fire",
      "type": "basic",
      "x": -260.3460156601416,
      "y": 28.961911613992697,
      "fixed": false,
      "shape": "dot",
      "color": "#7dd3fc",
      "size": 14
    },
    {
      "id": 179,
      "label": "B",
      "group": "Fire",
      "type": "basic",
      "x": -363.1953805655308,
      "y": -199.17841392833242,
      "fixed": false,
      "shape": "dot",
      "color": "#7dd3fc",
      "size": 14
    },
    {
      "id": 180,
      "label": "B",
      "group": "Fire",
      "type": "basic",
      "x": -441.7075768968357,
      "y": -477.16552698797517,
      "fixed": false,
      "shape": "dot",
      "color": "#7dd3fc",
      "size": 14
    },
    {
      "id": 181,
      "label": "Notable",
      "group": "Fire",
      "type": "notable",
      "x": -141.17236912102584,
      "y": -366.6232776570035,
      "fixed": false,
      "shape": "dot",
      "color": "#7dd3fc",
      "size": 14
    },
    {
      "id": 182,
      "label": "B",
      "group": "Fire",
      "type": "basic",
      "x": -466.2723321113982,
      "y": -617.71293109509,
      "fixed": false,
      "shape": "dot",
      "color": "#7dd3fc",
      "size": 14
    },
    {
      "id": 183,
      "label": "B",
      "group": "Fire",
      "type": "basic",
      "x": -620.3460156601418,
      "y": -594.5763791108028,
      "fixed": false,
      "shape": "dot",
      "color": "#7dd3fc",
      "size": 14
    },
    {
      "id": 184,
      "label": "B",
      "group": "Fire",
      "type": "basic",
      "x": -688.6787200671357,
      "y": -814.9320949623018,
      "fixed": false,
      "shape": "dot",
      "color": "#7dd3fc",
      "size": 14
    },
    {
      "id": 185,
      "label": "B",
      "group": "Fire",
      "type": "basic",
      "x": -779.0947269661064,
      "y": -813.5372127288169,
      "fixed": false,
      "shape": "dot",
      "color": "#7dd3fc",
      "size": 14
    },
    {
      "id": 186,
      "label": "Notable",
      "group": "Fire",
      "type": "notable",
      "x": -745.2883020007412,
      "y": -630.98276706654,
      "fixed": false,
      "shape": "dot",
      "color": "#7dd3fc",
      "size": 14
    },
    {
      "id": 188,
      "label": "Notable",
      "group": "Fire",
      "type": "notable",
      "x": -3.8422421021034125,
      "y": -138.76052025034284,
      "fixed": false,
      "shape": "dot",
      "color": "#7dd3fc",
      "size": 14
    },
    {
      "id": 189,
      "label": "B",
      "group": "Fire",
      "type": "basic",
      "x": 12.666686232077467,
      "y": -498.1662175970279,
      "fixed": false,
      "shape": "dot",
      "color": "#7dd3fc",
      "size": 14
    },
    {
      "id": 191,
      "label": "B",
      "group": "Fire",
      "type": "basic",
      "x": -546.8176274654909,
      "y": 871.2214749590221,
      "fixed": false,
      "shape": "dot",
      "color": "#7dd3fc",
      "size": 14
    },
    {
      "id": 192,
      "label": "B",
      "group": "Fire",
      "type": "basic",
      "x": -496.838752130977,
      "y": 538.6555235744925,
      "fixed": false,
      "shape": "dot",
      "color": "#7dd3fc",
      "size": 14
    },
    {
      "id": 193,
      "label": "B",
      "group": "Fire",
      "type": "basic",
      "x": -395.51566666721703,
      "y": 291.1587915716162,
      "fixed": false,
      "shape": "dot",
      "color": "#7dd3fc",
      "size": 14
    },
    {
      "id": 194,
      "label": "B",
      "group": "Fire",
      "type": "basic",
      "x": -264.8361747429059,
      "y": 24.815272051422156,
      "fixed": false,
      "shape": "dot",
      "color": "#7dd3fc",
      "size": 14
    },
    {
      "id": 195,
      "label": "B",
      "group": "Fire",
      "type": "basic",
      "x": -196.3002763580438,
      "y": -101.89238609353703,
      "fixed": false,
      "shape": "dot",
      "color": "#7dd3fc",
      "size": 14
    },
    {
      "id": 196,
      "label": "B",
      "group": "Fire",
      "type": "basic",
      "x": 389.82904902294365,
      "y": 246.9018425405227,
      "fixed": false,
      "shape": "dot",
      "color": "#7dd3fc",
      "size": 14
    },
    {
      "id": 197,
      "label": "B",
      "group": "Fire",
      "type": "basic",
      "x": 325.7649844174333,
      "y": 37.8640573766413,
      "fixed": false,
      "shape": "dot",
      "color": "#7dd3fc",
      "size": 14
    },
    {
      "id": 198,
      "label": "B",
      "group": "Fire",
      "type": "basic",
      "x": 718.5969982153745,
      "y": -326.5409493609914,
      "fixed": false,
      "shape": "dot",
      "color": "#7dd3fc",
      "size": 14
    },
    {
      "id": 199,
      "label": "B",
      "group": "Fire",
      "type": "basic",
      "x": 489.71569353129894,
      "y": -820.1069007455209,
      "fixed": false,
      "shape": "dot",
      "color": "#7dd3fc",
      "size": 14
    },
    {
      "id": 200,
      "label": "B",
      "group": "Fire",
      "type": "basic",
      "x": 525.5617904395644,
      "y": -402.19416184367384,
      "fixed": false,
      "shape": "dot",
      "color": "#7dd3fc",
      "size": 14
    },
    {
      "id": 201,
      "label": "B",
      "group": "Fire",
      "type": "basic",
      "x": -281.74909869289013,
      "y": 926.1093156373445,
      "fixed": false,
      "shape": "dot",
      "color": "#7dd3fc",
      "size": 14
    },
    {
      "id": 202,
      "label": "B",
      "group": "Fire",
      "type": "basic",
      "x": -246.57664832374098,
      "y": 743.1888445712831,
      "fixed": false,
      "shape": "dot",
      "color": "#7dd3fc",
      "size": 14
    },
    {
      "id": 203,
      "label": "B",
      "group": "Fire",
      "type": "basic",
      "x": -71.92154906203945,
      "y": 684.6773388490307,
      "fixed": false,
      "shape": "dot",
      "color": "#7dd3fc",
      "size": 14
    },
    {
      "id": 204,
      "label": "B",
      "group": "Fire",
      "type": "basic",
      "x": -303.762491194162,
      "y": 382.23762989650254,
      "fixed": false,
      "shape": "dot",
      "color": "#7dd3fc",
      "size": 14
    },
    {
      "id": 205,
      "label": "Notable",
      "group": "Fire",
      "type": "notable",
      "x": -314.58111249083146,
      "y": 666.9760316501811,
      "fixed": false,
      "shape": "dot",
      "color": "#7dd3fc",
      "size": 14
    },
    {
      "id": 206,
      "label": "B",
      "group": "Fire",
      "type": "basic",
      "x": -203.8964657903777,
      "y": 211.26459994718363,
      "fixed": false,
      "shape": "dot",
      "color": "#7dd3fc",
      "size": 14
    },
    {
      "id": 207,
      "label": "B",
      "group": "Fire",
      "type": "basic",
      "x": 28.238704975804865,
      "y": 531.1946899564782,
      "fixed": false,
      "shape": "dot",
      "color": "#7dd3fc",
      "size": 14
    },
    {
      "id": 208,
      "label": "B",
      "group": "Fire",
      "type": "basic",
      "x": 228.14767031961338,
      "y": 260.94220509247555,
      "fixed": false,
      "shape": "dot",
      "color": "#7dd3fc",
      "size": 14
    },
    {
      "id": 209,
      "label": "B",
      "group": "Fire",
      "type": "basic",
      "x": 49.2246218654807,
      "y": 330.84601566014135,
      "fixed": false,
      "shape": "dot",
      "color": "#7dd3fc",
      "size": 14
    },
    {
      "id": 210,
      "label": "Notable",
      "group": "Fire",
      "type": "notable",
      "x": -44.786883856771894,
      "y": 217.67872006713515,
      "fixed": false,
      "shape": "dot",
      "color": "#7dd3fc",
      "size": 14
    },
    {
      "id": 211,
      "label": "B",
      "group": "Fire",
      "type": "basic",
      "x": 44.84966812751499,
      "y": -51.576342184938945,
      "fixed": false,
      "shape": "dot",
      "color": "#7dd3fc",
      "size": 14
    },
    {
      "id": 212,
      "label": "B",
      "group": "Fire",
      "type": "basic",
      "x": -117.93425095425927,
      "y": -235.62632368012507,
      "fixed": false,
      "shape": "dot",
      "color": "#7dd3fc",
      "size": 14
    },
    {
      "id": 213,
      "label": "B",
      "group": "Fire",
      "type": "basic",
      "x": 28.216384140351437,
      "y": -438.76664922245044,
      "fixed": false,
      "shape": "dot",
      "color": "#7dd3fc",
      "size": 14
    },
    {
      "id": 214,
      "label": "B",
      "group": "Fire",
      "type": "basic",
      "x": 229.70418780904654,
      "y": -645.7537622820932,
      "fixed": false,
      "shape": "dot",
      "color": "#7dd3fc",
      "size": 14
    },
    {
      "id": 215,
      "label": "Notable",
      "group": "Fire",
      "type": "notable",
      "x": 284.23939558485665,
      "y": -330.21151295112156,
      "fixed": false,
      "shape": "dot",
      "color": "#7dd3fc",
      "size": 14
    },
    {
      "id": 216,
      "label": "B",
      "group": "Fire",
      "type": "basic",
      "x": 339.139432594484,
      "y": -737.301166389208,
      "fixed": false,
      "shape": "dot",
      "color": "#7dd3fc",
      "size": 14
    },
    {
      "id": 217,
      "label": "B",
      "group": "Fire",
      "type": "basic",
      "x": 242.0657490457403,
      "y": -859.1646144049209,
      "fixed": false,
      "shape": "dot",
      "color": "#7dd3fc",
      "size": 14
    },
    {
      "id": 218,
      "label": "B",
      "group": "Fire",
      "type": "basic",
      "x": 398.7330446387467,
      "y": -1028.52033025642,
      "fixed": false,
      "shape": "dot",
      "color": "#7dd3fc",
      "size": 14
    },
    {
      "id": 219,
      "label": "B",
      "group": "Fire",
      "type": "basic",
      "x": 352.31703773977597,
      "y": -1106.1254480229354,
      "fixed": false,
      "shape": "dot",
      "color": "#7dd3fc",
      "size": 14
    },
    {
      "id": 220,
      "label": "Notable",
      "group": "Fire",
      "type": "notable",
      "x": 211.1234627051407,
      "y": -985.571002360658,
      "fixed": false,
      "shape": "dot",
      "color": "#7dd3fc",
      "size": 14
    },
    {
      "id": 222,
      "label": "Notable",
      "group": "Fire",
      "type": "notable",
      "x": 155.56952260377898,
      "y": -97.34875554446062,
      "fixed": false,
      "shape": "dot",
      "color": "#7dd3fc",
      "size": 14
    },
    {
      "id": 223,
      "label": "B",
      "group": "Fire",
      "type": "basic",
      "x": 475.0784509379601,
      "y": -262.75445289114583,
      "fixed": false,
      "shape": "dot",
      "color": "#7dd3fc",
      "size": 14
    },
    {
      "id": 224,
      "group": "Hub",
      "type": "basic",
      "x": 0,
      "y": 0,
      "fixed": false,
      "shape": "dot",
      "color": "#7dd3fc",
      "size": 14
    }
  ],
  "edges": [
    {
      "id": "0fbe4a10-eb48-42c9-8e86-0e87975141f4",
      "from": 7,
      "to": 8,
      "width": 1.5,
      "smooth": false
    },
    {
      "id": "da8c5527-4492-45f8-85c3-1430cf1691d4",
      "from": 8,
      "to": 9,
      "width": 1.5,
      "smooth": false
    },
    {
      "id": "a7776440-ede2-4ff9-99a0-d3c5357702a9",
      "from": 9,
      "to": 10,
      "width": 1.5,
      "smooth": false
    },
    {
      "id": "5582cb8d-7ed3-426f-bdf7-a7bc8af0f5bf",
      "from": 10,
      "to": 11,
      "width": 1.5,
      "smooth": false
    },
    {
      "id": "25ace17e-3197-40cd-b49d-1b12216541ef",
      "from": 11,
      "to": 12,
      "width": 1.5,
      "smooth": false
    },
    {
      "id": "dc11b704-9c9d-4f70-aa2f-fd4b91b0e315",
      "from": 15,
      "to": 16,
      "width": 1.5,
      "smooth": false
    },
    {
      "id": "bd4b2084-adff-48d5-b8ad-98a076aa1d94",
      "from": 24,
      "to": 25,
      "width": 1.5,
      "smooth": false
    },
    {
      "id": "4a1c77c9-de6d-4103-a0e6-6137967173a9",
      "from": 25,
      "to": 26,
      "width": 1.5,
      "smooth": false
    },
    {
      "id": "27c45cf2-95ed-44d8-a553-717c88d09897",
      "from": 26,
      "to": 27,
      "width": 1.5,
      "smooth": false
    },
    {
      "id": "a1888421-876d-48ad-85e9-dcee3eb6cf38",
      "from": 7,
      "to": 24,
      "width": 1.5,
      "smooth": false
    },
    {
      "id": "43efae5a-5e79-4b3f-9ac5-e550cae78206",
      "from": 27,
      "to": 28,
      "width": 1.5,
      "smooth": false
    },
    {
      "id": "072a3459-c4d1-47a1-92c1-c2cc98edb932",
      "from": 29,
      "to": 30,
      "width": 1.5,
      "smooth": false
    },
    {
      "id": "1cfcce18-8403-420c-b3f9-e3771763b651",
      "from": 30,
      "to": 31,
      "width": 1.5,
      "smooth": false
    },
    {
      "id": "28859a45-7478-47de-88e6-05cb5930a9f5",
      "from": 31,
      "to": 32,
      "width": 1.5,
      "smooth": false
    },
    {
      "id": "5bbeb82f-5e85-4204-b4da-239138bf404c",
      "from": 10,
      "to": 29,
      "width": 1.5,
      "smooth": false
    },
    {
      "id": "66153418-fe97-44db-97a6-76948852725d",
      "from": 31,
      "to": 10,
      "width": 1.5,
      "smooth": false
    },
    {
      "id": "fc932615-fe27-4cee-a381-71f1b400cbb3",
      "from": 32,
      "to": 33,
      "width": 1.5,
      "smooth": false
    },
    {
      "id": "1ebfa93b-8ae8-45b2-b4dd-88b2a784aa2f",
      "from": 34,
      "to": 35,
      "width": 1.5,
      "smooth": false
    },
    {
      "id": "441e828a-4682-4f9d-a0e0-d205da63cd91",
      "from": 35,
      "to": 36,
      "width": 1.5,
      "smooth": false
    },
    {
      "id": "bd5f3ab7-616e-49cf-8437-035aa2239183",
      "from": 36,
      "to": 37,
      "width": 1.5,
      "smooth": false
    },
    {
      "id": "11389f11-e423-4de2-9d81-33beeba523f4",
      "from": 13,
      "to": 34,
      "width": 1.5,
      "smooth": false
    },
    {
      "id": "24aa9cd3-78ec-4fab-9df8-bb3d29f4b55b",
      "from": 36,
      "to": 13,
      "width": 1.5,
      "smooth": false
    },
    {
      "id": "6d98cd7b-dbe5-41a7-bc7e-3e1223112e5e",
      "from": 37,
      "to": 38,
      "width": 1.5,
      "smooth": false
    },
    {
      "id": "fe192410-07d0-4aa6-a5be-20ff20975081",
      "from": 39,
      "to": 40,
      "width": 1.5,
      "smooth": false
    },
    {
      "id": "fcb8f37e-7f46-425e-b9c4-19a856bb1279",
      "from": 40,
      "to": 41,
      "width": 1.5,
      "smooth": false
    },
    {
      "id": "e77d482a-6a13-4ab2-98cc-3afea56e19b8",
      "from": 41,
      "to": 42,
      "width": 1.5,
      "smooth": false
    },
    {
      "id": "bbe47f53-caf0-454c-a70c-d1f33040c8bd",
      "from": 16,
      "to": 39,
      "width": 1.5,
      "smooth": false
    },
    {
      "id": "812a2183-986b-47f3-b37a-80eb2ee156d0",
      "from": 41,
      "to": 16,
      "width": 1.5,
      "smooth": false
    },
    {
      "id": "cf6a30cc-26c6-4694-b539-80fd7f5b6f92",
      "from": 42,
      "to": 43,
      "width": 1.5,
      "smooth": false
    },
    {
      "id": "dd4060a7-2cfe-4021-8379-947e54aa50f5",
      "from": 11,
      "to": 35,
      "width": 1.5,
      "smooth": false
    },
    {
      "id": "cb7c903a-51fe-4fa5-a7eb-bb1b566c9787",
      "from": 13,
      "to": 52,
      "width": 1.5,
      "smooth": false
    },
    {
      "id": "f09d308e-0cd6-4614-aa8f-4c0b5defd152",
      "from": 37,
      "to": 39,
      "width": 1.5,
      "smooth": false
    },
    {
      "id": "2fa6df95-b5bd-4f2e-a024-d862e71284a7",
      "from": 15,
      "to": 53,
      "width": 1.5,
      "smooth": false
    },
    {
      "id": "97314051-e750-4e22-9c9a-38abf92f664b",
      "from": 15,
      "to": 17,
      "width": 1.5,
      "smooth": false
    },
    {
      "id": "7409389b-405d-4158-8d01-e6cfc3d0a353",
      "from": 12,
      "to": 15,
      "width": 1.5,
      "smooth": false
    },
    {
      "id": "1f601fcb-38df-4944-9f3f-efcd3eaa2e8a",
      "from": 55,
      "to": 56,
      "width": 1.5,
      "smooth": false
    },
    {
      "id": "60a5c994-70c6-4eab-b8a0-757e3707559f",
      "from": 56,
      "to": 57,
      "width": 1.5,
      "smooth": false
    },
    {
      "id": "bf2542ff-f353-4c29-86fe-93b156fadcd9",
      "from": 57,
      "to": 58,
      "width": 1.5,
      "smooth": false
    },
    {
      "id": "81e3d46c-df98-4523-ba75-e3a44464c87d",
      "from": 58,
      "to": 59,
      "width": 1.5,
      "smooth": false
    },
    {
      "id": "8fbf931a-23e8-4a1e-8043-891b295e9597",
      "from": 59,
      "to": 60,
      "width": 1.5,
      "smooth": false
    },
    {
      "id": "64910ae2-5791-4dbc-bdc8-9a8ff76c31dd",
      "from": 62,
      "to": 63,
      "width": 1.5,
      "smooth": false
    },
    {
      "id": "f4b13343-761e-4766-b5f5-2da8b4cf98e6",
      "from": 65,
      "to": 66,
      "width": 1.5,
      "smooth": false
    },
    {
      "id": "4fbdba02-4685-4774-80f4-e0c736eccfbb",
      "from": 66,
      "to": 67,
      "width": 1.5,
      "smooth": false
    },
    {
      "id": "ce4ce00a-e073-42ba-9a0f-f6b94e8c3a08",
      "from": 67,
      "to": 68,
      "width": 1.5,
      "smooth": false
    },
    {
      "id": "5e276dda-890c-4523-8fb3-0cd1742e72c4",
      "from": 55,
      "to": 65,
      "width": 1.5,
      "smooth": false
    },
    {
      "id": "66170c2a-69c7-4e33-b569-17b9a004fa42",
      "from": 68,
      "to": 69,
      "width": 1.5,
      "smooth": false
    },
    {
      "id": "79d003a8-446c-4955-ba62-7dc20333bbe6",
      "from": 70,
      "to": 71,
      "width": 1.5,
      "smooth": false
    },
    {
      "id": "319b82fb-1fa5-4b71-8d6e-56b862417f9f",
      "from": 71,
      "to": 72,
      "width": 1.5,
      "smooth": false
    },
    {
      "id": "24ccdbd4-9c9f-49f1-95ec-ef1c533cf7e8",
      "from": 72,
      "to": 73,
      "width": 1.5,
      "smooth": false
    },
    {
      "id": "6e2beb14-9c7a-4232-9851-cc0acbc3e6f8",
      "from": 58,
      "to": 70,
      "width": 1.5,
      "smooth": false
    },
    {
      "id": "4c210a48-03ff-4bd4-adac-6d95573d54c5",
      "from": 72,
      "to": 58,
      "width": 1.5,
      "smooth": false
    },
    {
      "id": "ddaf030d-f30f-44a5-825e-a2ac50a43eca",
      "from": 73,
      "to": 74,
      "width": 1.5,
      "smooth": false
    },
    {
      "id": "ef3dbc97-c016-4a88-bee4-a111d5d1417d",
      "from": 75,
      "to": 76,
      "width": 1.5,
      "smooth": false
    },
    {
      "id": "3dd528ca-2b5c-4df8-a3b0-645f8c33b035",
      "from": 76,
      "to": 77,
      "width": 1.5,
      "smooth": false
    },
    {
      "id": "1f6f6024-3b50-4092-aeb9-0d75d69a4681",
      "from": 77,
      "to": 78,
      "width": 1.5,
      "smooth": false
    },
    {
      "id": "6783b864-53c3-4864-a7bc-a5e818a6b57a",
      "from": 61,
      "to": 75,
      "width": 1.5,
      "smooth": false
    },
    {
      "id": "1a8e00da-9c51-4919-9e42-7ab2e34f9c8f",
      "from": 77,
      "to": 61,
      "width": 1.5,
      "smooth": false
    },
    {
      "id": "f1791c11-cf9c-4c79-8628-ce46fc75cbd5",
      "from": 78,
      "to": 79,
      "width": 1.5,
      "smooth": false
    },
    {
      "id": "0640a6c1-d6d6-4fa0-8aae-570a1cb524ed",
      "from": 80,
      "to": 81,
      "width": 1.5,
      "smooth": false
    },
    {
      "id": "9477fbf5-85ea-4a3d-b60f-3b69052a1640",
      "from": 81,
      "to": 82,
      "width": 1.5,
      "smooth": false
    },
    {
      "id": "8ef638f2-4321-4426-a917-b1cac5393ef1",
      "from": 82,
      "to": 83,
      "width": 1.5,
      "smooth": false
    },
    {
      "id": "559b9b79-8e28-4565-ba1f-982ab19a232f",
      "from": 63,
      "to": 80,
      "width": 1.5,
      "smooth": false
    },
    {
      "id": "37ea999d-43cd-44c2-b815-ae9bb4d8c4cd",
      "from": 82,
      "to": 63,
      "width": 1.5,
      "smooth": false
    },
    {
      "id": "4cc56d09-80ce-46d7-852c-8e339ff89103",
      "from": 83,
      "to": 84,
      "width": 1.5,
      "smooth": false
    },
    {
      "id": "bafeeb32-742a-4e9b-80ed-772a6ddce75e",
      "from": 59,
      "to": 76,
      "width": 1.5,
      "smooth": false
    },
    {
      "id": "124372ed-de1b-452d-af67-28bc673567d0",
      "from": 61,
      "to": 86,
      "width": 1.5,
      "smooth": false
    },
    {
      "id": "04c27e67-f925-4a6d-9f72-5f8ebf5df9eb",
      "from": 78,
      "to": 80,
      "width": 1.5,
      "smooth": false
    },
    {
      "id": "2fd96f3a-0d6b-4ba1-97e2-49ee64a11031",
      "from": 62,
      "to": 87,
      "width": 1.5,
      "smooth": false
    },
    {
      "id": "4a759bfe-e0f2-4b48-993e-aa0b93e42810",
      "from": 62,
      "to": 64,
      "width": 1.5,
      "smooth": false
    },
    {
      "id": "8d230b2f-19b4-4c70-b2eb-3320f4402315",
      "from": 60,
      "to": 62,
      "width": 1.5,
      "smooth": false
    },
    {
      "id": "05cfad60-9872-42b2-a92d-6261f2a4d01a",
      "from": 89,
      "to": 90,
      "width": 1.5,
      "smooth": false
    },
    {
      "id": "5dcfc147-9543-47bb-81eb-d7ce6758954f",
      "from": 90,
      "to": 91,
      "width": 1.5,
      "smooth": false
    },
    {
      "id": "3699de8c-6dee-414b-8d90-97b5b6a3fedb",
      "from": 91,
      "to": 92,
      "width": 1.5,
      "smooth": false
    },
    {
      "id": "f824fe43-c6d1-4a8e-ac6e-3cbef1300e2a",
      "from": 92,
      "to": 93,
      "width": 1.5,
      "smooth": false
    },
    {
      "id": "95ff4024-b162-4853-9c54-ca0fe49b417f",
      "from": 93,
      "to": 94,
      "width": 1.5,
      "smooth": false
    },
    {
      "id": "c4824d94-2c52-4165-ae35-14b0f8406ceb",
      "from": 96,
      "to": 97,
      "width": 1.5,
      "smooth": false
    },
    {
      "id": "173a98f7-9c4a-49f1-99ef-781e17f380e9",
      "from": 99,
      "to": 100,
      "width": 1.5,
      "smooth": false
    },
    {
      "id": "55b02206-2f2f-48fa-a3dd-2921fc13de32",
      "from": 100,
      "to": 101,
      "width": 1.5,
      "smooth": false
    },
    {
      "id": "bc10e0f2-14fb-477a-a6d9-1bfc8cb7acfe",
      "from": 101,
      "to": 102,
      "width": 1.5,
      "smooth": false
    },
    {
      "id": "2a17a8fc-6636-49dc-a7f5-f3866dfc23ad",
      "from": 89,
      "to": 99,
      "width": 1.5,
      "smooth": false
    },
    {
      "id": "fe275f2b-24a5-495d-8ed3-2da8bdd18ee4",
      "from": 102,
      "to": 103,
      "width": 1.5,
      "smooth": false
    },
    {
      "id": "b1f86f55-3498-4be1-b22d-d07241988dc1",
      "from": 104,
      "to": 105,
      "width": 1.5,
      "smooth": false
    },
    {
      "id": "8109b6fd-07f7-44d1-a6e3-2339073e7494",
      "from": 105,
      "to": 106,
      "width": 1.5,
      "smooth": false
    },
    {
      "id": "43e237de-8c1d-4f97-bfdc-f25711b58ecd",
      "from": 106,
      "to": 107,
      "width": 1.5,
      "smooth": false
    },
    {
      "id": "8dcf97ad-3010-4411-a95c-4ff50c75b1dc",
      "from": 92,
      "to": 104,
      "width": 1.5,
      "smooth": false
    },
    {
      "id": "066c8bdb-22e8-4a61-bbbb-f82787433d68",
      "from": 106,
      "to": 92,
      "width": 1.5,
      "smooth": false
    },
    {
      "id": "5b466576-41d2-4c54-9e52-1a78a2d34710",
      "from": 107,
      "to": 108,
      "width": 1.5,
      "smooth": false
    },
    {
      "id": "ac60bf82-dbda-44f0-9e7c-a8c70ff29e8b",
      "from": 109,
      "to": 110,
      "width": 1.5,
      "smooth": false
    },
    {
      "id": "27f2f41c-a28b-4387-9e5e-e34f4fc49d81",
      "from": 110,
      "to": 111,
      "width": 1.5,
      "smooth": false
    },
    {
      "id": "16ff4a0b-8442-45a7-b68b-b6c30f974b04",
      "from": 111,
      "to": 112,
      "width": 1.5,
      "smooth": false
    },
    {
      "id": "2276b27c-3b25-4c59-be94-1bff4c6e8559",
      "from": 95,
      "to": 109,
      "width": 1.5,
      "smooth": false
    },
    {
      "id": "d5a2c764-f83f-4bee-9309-8deb3be6c0c3",
      "from": 111,
      "to": 95,
      "width": 1.5,
      "smooth": false
    },
    {
      "id": "bd65a0c4-0100-4860-b7f1-748a3dd7f1fd",
      "from": 112,
      "to": 113,
      "width": 1.5,
      "smooth": false
    },
    {
      "id": "be989fe2-c4c5-4fbb-b1c5-6da172d04a50",
      "from": 114,
      "to": 115,
      "width": 1.5,
      "smooth": false
    },
    {
      "id": "11f0a310-6352-4e40-ac46-cd7abe709fdf",
      "from": 115,
      "to": 116,
      "width": 1.5,
      "smooth": false
    },
    {
      "id": "9eb3c12c-0e24-4b78-801f-3e3ead2dd9b0",
      "from": 116,
      "to": 117,
      "width": 1.5,
      "smooth": false
    },
    {
      "id": "10d832be-4dcb-4765-a0b8-d72e309f0c8a",
      "from": 97,
      "to": 114,
      "width": 1.5,
      "smooth": false
    },
    {
      "id": "c0f6fad2-694a-4a97-a357-596d78016124",
      "from": 116,
      "to": 97,
      "width": 1.5,
      "smooth": false
    },
    {
      "id": "27974b26-95e2-4db5-a166-f4a2a6eed914",
      "from": 117,
      "to": 118,
      "width": 1.5,
      "smooth": false
    },
    {
      "id": "a9b92eb6-d7ec-44be-af5e-4b2e3ed10d68",
      "from": 93,
      "to": 110,
      "width": 1.5,
      "smooth": false
    },
    {
      "id": "d9b63c80-064f-4afa-bc7f-adb7f4489276",
      "from": 95,
      "to": 120,
      "width": 1.5,
      "smooth": false
    },
    {
      "id": "950090d8-9c49-49ad-9664-a8292a5b93d6",
      "from": 112,
      "to": 114,
      "width": 1.5,
      "smooth": false
    },
    {
      "id": "f795d88a-2e92-4a0c-93f3-ae128a49cbd1",
      "from": 96,
      "to": 121,
      "width": 1.5,
      "smooth": false
    },
    {
      "id": "832dead7-e4fa-44d8-b7b1-f9c7771fe8eb",
      "from": 96,
      "to": 98,
      "width": 1.5,
      "smooth": false
    },
    {
      "id": "812823e0-23e4-4a3d-991e-6c8dbbaa3ea1",
      "from": 94,
      "to": 96,
      "width": 1.5,
      "smooth": false
    },
    {
      "id": "e10029f9-34eb-408b-b91a-5a7625c02e6d",
      "from": 123,
      "to": 124,
      "width": 1.5,
      "smooth": false
    },
    {
      "id": "7f10441d-68b4-4f8b-a313-5d77194f10df",
      "from": 124,
      "to": 125,
      "width": 1.5,
      "smooth": false
    },
    {
      "id": "ab80608d-93f3-42bb-8b80-408fea0e2faa",
      "from": 125,
      "to": 126,
      "width": 1.5,
      "smooth": false
    },
    {
      "id": "082e5db0-5c2a-492b-822e-b7e1270371b0",
      "from": 126,
      "to": 127,
      "width": 1.5,
      "smooth": false
    },
    {
      "id": "c53098c4-1cb2-43d0-936f-489f6b8debd9",
      "from": 127,
      "to": 128,
      "width": 1.5,
      "smooth": false
    },
    {
      "id": "e1ab4fa3-8752-4796-8adb-5e5b9394e4b4",
      "from": 130,
      "to": 131,
      "width": 1.5,
      "smooth": false
    },
    {
      "id": "7076ac73-d97e-47f1-a315-9783ee93013c",
      "from": 133,
      "to": 134,
      "width": 1.5,
      "smooth": false
    },
    {
      "id": "55706e00-af10-4cec-8de5-c526f5f7209b",
      "from": 134,
      "to": 135,
      "width": 1.5,
      "smooth": false
    },
    {
      "id": "3f8c2cae-9676-4ee3-b9ef-a22a1a7cdea9",
      "from": 135,
      "to": 136,
      "width": 1.5,
      "smooth": false
    },
    {
      "id": "e7ca548f-8972-466f-92fa-7349611f744e",
      "from": 123,
      "to": 133,
      "width": 1.5,
      "smooth": false
    },
    {
      "id": "76063bc1-b11e-45e8-b66e-9dc9df93fdfb",
      "from": 136,
      "to": 137,
      "width": 1.5,
      "smooth": false
    },
    {
      "id": "a75c52b5-ba9d-4617-a0c5-8c3e55094501",
      "from": 138,
      "to": 139,
      "width": 1.5,
      "smooth": false
    },
    {
      "id": "8bf1f7f2-550b-48e4-99e5-23203fe76714",
      "from": 139,
      "to": 140,
      "width": 1.5,
      "smooth": false
    },
    {
      "id": "f669a4b4-1589-4e2f-9042-2f3bc13a535d",
      "from": 140,
      "to": 141,
      "width": 1.5,
      "smooth": false
    },
    {
      "id": "010e1fb1-4a40-4d66-bbff-b2a48b6e372e",
      "from": 126,
      "to": 138,
      "width": 1.5,
      "smooth": false
    },
    {
      "id": "d7550204-76eb-497c-bfa1-ab0997da5c9a",
      "from": 140,
      "to": 126,
      "width": 1.5,
      "smooth": false
    },
    {
      "id": "8a7d6945-8196-4ea2-ab6d-e31fc879e37a",
      "from": 141,
      "to": 142,
      "width": 1.5,
      "smooth": false
    },
    {
      "id": "5c4f5aba-b6ab-40a1-b8d4-6bec5268ffc9",
      "from": 143,
      "to": 144,
      "width": 1.5,
      "smooth": false
    },
    {
      "id": "80c2d284-d056-4d18-84b9-29a724e601c9",
      "from": 144,
      "to": 145,
      "width": 1.5,
      "smooth": false
    },
    {
      "id": "b12c2b72-70fc-4b0a-bd64-ad3b689a3eb6",
      "from": 145,
      "to": 146,
      "width": 1.5,
      "smooth": false
    },
    {
      "id": "46e468fa-3bdb-4510-bd2f-c96150f38771",
      "from": 129,
      "to": 143,
      "width": 1.5,
      "smooth": false
    },
    {
      "id": "cdd6547b-6512-4326-9037-a56c185550d7",
      "from": 145,
      "to": 129,
      "width": 1.5,
      "smooth": false
    },
    {
      "id": "fd1b8f66-01ff-4f7e-9486-dde7227e5a5e",
      "from": 146,
      "to": 147,
      "width": 1.5,
      "smooth": false
    },
    {
      "id": "f21a1346-73c2-4382-ab8f-0210f0414f89",
      "from": 148,
      "to": 149,
      "width": 1.5,
      "smooth": false
    },
    {
      "id": "8f341304-9ad9-4d5b-802b-99cf1ceab1ea",
      "from": 149,
      "to": 150,
      "width": 1.5,
      "smooth": false
    },
    {
      "id": "91bbffce-d5dd-4ac2-890f-3db90ee72c5a",
      "from": 150,
      "to": 151,
      "width": 1.5,
      "smooth": false
    },
    {
      "id": "10a7560d-9d2b-4986-a5d1-2f0e29995dbc",
      "from": 131,
      "to": 148,
      "width": 1.5,
      "smooth": false
    },
    {
      "id": "4e42a956-2998-408c-9e19-337189aff4a5",
      "from": 150,
      "to": 131,
      "width": 1.5,
      "smooth": false
    },
    {
      "id": "776c27c0-477a-4afe-aa2e-15c0b96a4132",
      "from": 151,
      "to": 152,
      "width": 1.5,
      "smooth": false
    },
    {
      "id": "93061a14-4f4e-4131-912b-bad1e23f1c4d",
      "from": 127,
      "to": 144,
      "width": 1.5,
      "smooth": false
    },
    {
      "id": "573c59cd-d97a-4ed4-9757-539afaefb95e",
      "from": 129,
      "to": 154,
      "width": 1.5,
      "smooth": false
    },
    {
      "id": "20776eda-980f-42c7-8307-9d3236399547",
      "from": 146,
      "to": 148,
      "width": 1.5,
      "smooth": false
    },
    {
      "id": "be106097-caf0-4703-b9b4-0d52ebc22a08",
      "from": 130,
      "to": 155,
      "width": 1.5,
      "smooth": false
    },
    {
      "id": "1c6e2c9d-f4ff-48b6-b338-e5c6583c3872",
      "from": 130,
      "to": 132,
      "width": 1.5,
      "smooth": false
    },
    {
      "id": "e7f12f5e-33a8-4ae9-a276-d7a183107f48",
      "from": 128,
      "to": 130,
      "width": 1.5,
      "smooth": false
    },
    {
      "id": "06b7e4f2-4db7-442f-ba69-31dd23c41a2a",
      "from": 157,
      "to": 158,
      "width": 1.5,
      "smooth": false
    },
    {
      "id": "f8840f73-c1f4-47e6-815c-12d1eea612fb",
      "from": 158,
      "to": 159,
      "width": 1.5,
      "smooth": false
    },
    {
      "id": "3dcbed47-775b-4c96-8654-3130b9a125c8",
      "from": 159,
      "to": 160,
      "width": 1.5,
      "smooth": false
    },
    {
      "id": "44e8ad21-842c-4010-aa94-acfb2e5109ea",
      "from": 160,
      "to": 161,
      "width": 1.5,
      "smooth": false
    },
    {
      "id": "72579dac-ed22-4b35-b7dd-4b823bd80465",
      "from": 161,
      "to": 162,
      "width": 1.5,
      "smooth": false
    },
    {
      "id": "a2af2beb-5f74-442a-af8b-b98b4bc15b14",
      "from": 167,
      "to": 168,
      "width": 1.5,
      "smooth": false
    },
    {
      "id": "999e219a-9616-4759-a006-66f308fd5a52",
      "from": 168,
      "to": 169,
      "width": 1.5,
      "smooth": false
    },
    {
      "id": "a66f6885-da35-44c0-b74c-cdb2c3538b9e",
      "from": 169,
      "to": 170,
      "width": 1.5,
      "smooth": false
    },
    {
      "id": "b7ddc833-da3d-4a43-9426-36b56c5c28b6",
      "from": 157,
      "to": 167,
      "width": 1.5,
      "smooth": false
    },
    {
      "id": "66ef4fae-fd22-41db-afd1-e7c563a1ec54",
      "from": 170,
      "to": 171,
      "width": 1.5,
      "smooth": false
    },
    {
      "id": "571018a6-b365-4a6d-a441-2b26e76ff77b",
      "from": 172,
      "to": 173,
      "width": 1.5,
      "smooth": false
    },
    {
      "id": "a28a14be-7608-45b5-9cfa-2e6d0472b54f",
      "from": 173,
      "to": 174,
      "width": 1.5,
      "smooth": false
    },
    {
      "id": "44136ee4-4e0f-40fa-9d9f-db2939e5cebc",
      "from": 174,
      "to": 175,
      "width": 1.5,
      "smooth": false
    },
    {
      "id": "a1b5db7f-2091-49ad-b160-2cae2b23fd58",
      "from": 160,
      "to": 172,
      "width": 1.5,
      "smooth": false
    },
    {
      "id": "98c146d5-da40-4a4f-9581-3fdd2a23c9e4",
      "from": 174,
      "to": 160,
      "width": 1.5,
      "smooth": false
    },
    {
      "id": "abdd8455-0b39-42db-a6e4-f1e18d0050ea",
      "from": 175,
      "to": 176,
      "width": 1.5,
      "smooth": false
    },
    {
      "id": "7e6863c5-8509-428d-bf5f-2631c209cc15",
      "from": 177,
      "to": 178,
      "width": 1.5,
      "smooth": false
    },
    {
      "id": "b1baec60-e08d-436c-b1e5-27bec9c0135f",
      "from": 178,
      "to": 179,
      "width": 1.5,
      "smooth": false
    },
    {
      "id": "dfa36153-0dfd-4a5f-b4b7-418d8785d65a",
      "from": 179,
      "to": 180,
      "width": 1.5,
      "smooth": false
    },
    {
      "id": "6acbf1db-9f17-4848-b0db-2ab6ead32a16",
      "from": 163,
      "to": 177,
      "width": 1.5,
      "smooth": false
    },
    {
      "id": "91873a4b-0872-446b-9c3d-6fc0dd92ca04",
      "from": 179,
      "to": 163,
      "width": 1.5,
      "smooth": false
    },
    {
      "id": "3defa220-9dc6-4da6-a6e7-80130ce9c1f0",
      "from": 180,
      "to": 181,
      "width": 1.5,
      "smooth": false
    },
    {
      "id": "598cac80-6293-47e5-8622-66fc242ceb6c",
      "from": 182,
      "to": 183,
      "width": 1.5,
      "smooth": false
    },
    {
      "id": "bb41efd6-16cf-47bd-a3f0-728263c8967e",
      "from": 183,
      "to": 184,
      "width": 1.5,
      "smooth": false
    },
    {
      "id": "cdca2082-030a-4d08-b83d-b7e664338ad2",
      "from": 184,
      "to": 185,
      "width": 1.5,
      "smooth": false
    },
    {
      "id": "7b5c387c-9e80-407a-9905-0d09c8017480",
      "from": 165,
      "to": 182,
      "width": 1.5,
      "smooth": false
    },
    {
      "id": "fe782949-1fb5-4a18-a6b8-be4be751b1a4",
      "from": 184,
      "to": 165,
      "width": 1.5,
      "smooth": false
    },
    {
      "id": "5211b9e4-9197-4253-a566-ded2a4750357",
      "from": 185,
      "to": 186,
      "width": 1.5,
      "smooth": false
    },
    {
      "id": "e888a1e9-913d-400e-9599-170c1b458dca",
      "from": 161,
      "to": 178,
      "width": 1.5,
      "smooth": false
    },
    {
      "id": "8a5e1059-e861-49e7-ad6e-bc369cf60a39",
      "from": 163,
      "to": 188,
      "width": 1.5,
      "smooth": false
    },
    {
      "id": "e79c024d-299f-4c31-b51c-7e15230fe025",
      "from": 180,
      "to": 182,
      "width": 1.5,
      "smooth": false
    },
    {
      "id": "97f2366a-abe8-4176-a4de-5cdacec7beb8",
      "from": 191,
      "to": 192,
      "width": 1.5,
      "smooth": false
    },
    {
      "id": "76ce3e49-7937-44d0-94f7-1ff21fce426e",
      "from": 192,
      "to": 193,
      "width": 1.5,
      "smooth": false
    },
    {
      "id": "c2e713cf-0460-49fb-8a8b-16d67af85ba3",
      "from": 193,
      "to": 194,
      "width": 1.5,
      "smooth": false
    },
    {
      "id": "eaa5c544-2b13-4b12-913c-b420855ac628",
      "from": 194,
      "to": 195,
      "width": 1.5,
      "smooth": false
    },
    {
      "id": "139922df-f740-480e-ab98-fd345ecb7bc8",
      "from": 195,
      "to": 196,
      "width": 1.5,
      "smooth": false
    },
    {
      "id": "966c753e-53bd-447c-8167-1aca912b9678",
      "from": 198,
      "to": 199,
      "width": 1.5,
      "smooth": false
    },
    {
      "id": "b55d6629-b873-4b1f-9f5b-6259a191b918",
      "from": 201,
      "to": 202,
      "width": 1.5,
      "smooth": false
    },
    {
      "id": "f336fd53-184a-4eca-bca5-848b7d92cb82",
      "from": 202,
      "to": 203,
      "width": 1.5,
      "smooth": false
    },
    {
      "id": "072127e5-d4e8-4b81-bb42-308c7ab53748",
      "from": 203,
      "to": 204,
      "width": 1.5,
      "smooth": false
    },
    {
      "id": "be271d46-4d20-4269-9490-2680701160e2",
      "from": 191,
      "to": 201,
      "width": 1.5,
      "smooth": false
    },
    {
      "id": "db7d4925-c7a5-4258-8469-682ec687c40d",
      "from": 204,
      "to": 205,
      "width": 1.5,
      "smooth": false
    },
    {
      "id": "cc06ac2d-6bb2-4cf2-9ca1-710be34da0c0",
      "from": 206,
      "to": 207,
      "width": 1.5,
      "smooth": false
    },
    {
      "id": "e2d12623-c42b-4273-8ee1-6cf6dbeabeff",
      "from": 207,
      "to": 208,
      "width": 1.5,
      "smooth": false
    },
    {
      "id": "1c693c01-4734-4d45-97ab-7b7722d34e9a",
      "from": 208,
      "to": 209,
      "width": 1.5,
      "smooth": false
    },
    {
      "id": "63cef17c-fe6b-484b-862f-c7e9656c3260",
      "from": 194,
      "to": 206,
      "width": 1.5,
      "smooth": false
    },
    {
      "id": "d05f81a9-85f6-4781-9c1c-9e043257db17",
      "from": 208,
      "to": 194,
      "width": 1.5,
      "smooth": false
    },
    {
      "id": "8d6971bb-41ab-4a14-b40a-1f70c0aa83fb",
      "from": 209,
      "to": 210,
      "width": 1.5,
      "smooth": false
    },
    {
      "id": "8f7f063d-4c1b-4c19-8bc4-81aace5e19f9",
      "from": 211,
      "to": 212,
      "width": 1.5,
      "smooth": false
    },
    {
      "id": "12cb2ab8-5e46-4b02-908f-1e58ff7733c6",
      "from": 212,
      "to": 213,
      "width": 1.5,
      "smooth": false
    },
    {
      "id": "feed9375-e850-47a1-ab83-c35d92f8af68",
      "from": 213,
      "to": 214,
      "width": 1.5,
      "smooth": false
    },
    {
      "id": "489bbf84-8265-461a-a849-fb4b7d260ebe",
      "from": 197,
      "to": 211,
      "width": 1.5,
      "smooth": false
    },
    {
      "id": "95523b06-18b7-4c11-8926-8ed3726fb8fc",
      "from": 213,
      "to": 197,
      "width": 1.5,
      "smooth": false
    },
    {
      "id": "b1d1758f-4469-4a2c-b45d-7607aae96223",
      "from": 214,
      "to": 215,
      "width": 1.5,
      "smooth": false
    },
    {
      "id": "f3904290-466e-49ab-869c-78bfd613432c",
      "from": 216,
      "to": 217,
      "width": 1.5,
      "smooth": false
    },
    {
      "id": "2d8535ac-2913-4632-a6ab-99c4fadc266e",
      "from": 217,
      "to": 218,
      "width": 1.5,
      "smooth": false
    },
    {
      "id": "3e9d7d26-c0bf-4c6d-8f3b-dcc5a07dda9f",
      "from": 218,
      "to": 219,
      "width": 1.5,
      "smooth": false
    },
    {
      "id": "dda26a78-f311-469e-bd63-3d17cbe30204",
      "from": 199,
      "to": 216,
      "width": 1.5,
      "smooth": false
    },
    {
      "id": "0a1fbeeb-df8f-4e8b-a21c-70336759b22f",
      "from": 218,
      "to": 199,
      "width": 1.5,
      "smooth": false
    },
    {
      "id": "2058f687-2bda-4ea7-9948-51dd28021d0f",
      "from": 219,
      "to": 220,
      "width": 1.5,
      "smooth": false
    },
    {
      "id": "c6f23209-2d4f-465f-9845-c1a9b0fd8c1e",
      "from": 195,
      "to": 212,
      "width": 1.5,
      "smooth": false
    },
    {
      "id": "752e6ed8-6a21-4c3b-85cd-129354ef7ff3",
      "from": 197,
      "to": 222,
      "width": 1.5,
      "smooth": false
    },
    {
      "id": "1aeddc53-dba8-4a48-83b2-fcff04617b0c",
      "from": 214,
      "to": 216,
      "width": 1.5,
      "smooth": false
    },
    {
      "id": "8d6de9ff-fdd1-45f2-945b-33d6fdf868fc",
      "from": 198,
      "to": 223,
      "width": 1.5,
      "smooth": false
    },
    {
      "id": "9a724a24-db33-4485-a6ad-b00d7451cf7c",
      "from": 198,
      "to": 200,
      "width": 1.5,
      "smooth": false
    },
    {
      "id": "c6d16f86-3bc9-45ac-8338-c6a9262099ac",
      "from": 196,
      "to": 198,
      "width": 1.5,
      "smooth": false
    },
    {
      "id": "f4ac76a0-d0db-42d0-9eea-4c357175a34c",
      "from": 162,
      "to": 130,
      "width": 1.5,
      "smooth": false
    },
    {
      "id": "e7da4f8e-b374-4af9-88ef-c3b20b706491",
      "from": 157,
      "to": 131,
      "width": 1.5,
      "smooth": false
    },
    {
      "id": "e4e6e947-bbd9-4d5b-96ee-9be8304c4cfb",
      "from": 153,
      "to": 122,
      "width": 1.5,
      "smooth": false
    },
    {
      "id": "91d949fa-c6d5-4e58-886e-4f7e3e20d8d1",
      "from": 123,
      "to": 97,
      "width": 1.5,
      "smooth": false
    },
    {
      "id": "e54a0aa4-2ba2-404f-a7e7-c13b9bf9696a",
      "from": 128,
      "to": 96,
      "width": 1.5,
      "smooth": false
    },
    {
      "id": "d6f08758-cefa-4a2c-ab98-0be016d18241",
      "from": 88,
      "to": 119,
      "width": 1.5,
      "smooth": false
    },
    {
      "id": "c3b8e09f-d55b-4c34-a932-5bd83523e9a0",
      "from": 94,
      "to": 62,
      "width": 1.5,
      "smooth": false
    },
    {
      "id": "9788b886-44ee-4430-a40f-2c9e9a6b8af4",
      "from": 89,
      "to": 63,
      "width": 1.5,
      "smooth": false
    },
    {
      "id": "0b2a05e0-3ce2-45d5-b9d9-04bee11b49bb",
      "from": 164,
      "to": 162,
      "width": 1.5,
      "smooth": false
    },
    {
      "id": "4721897f-ed0f-4b88-9a69-97d0e9e31f91",
      "from": 221,
      "to": 221,
      "width": 1.5,
      "smooth": false
    },
    {
      "id": "1f01a24c-d5f8-4643-8b54-f9236a933fcb",
      "from": 190,
      "to": 191,
      "width": 1.5,
      "smooth": false
    },
    {
      "id": "53a23ec7-6731-44e2-b0d2-bf1aa5c395b4",
      "from": 165,
      "to": 191,
      "width": 1.5,
      "smooth": false
    },
    {
      "id": "f4ec782c-4cf9-4de3-bd0d-cf79f1737d25",
      "from": 181,
      "to": 189,
      "width": 1.5,
      "smooth": false
    },
    {
      "id": "ed2976c4-1548-4b10-989c-50d0fc5a1b68",
      "from": 166,
      "to": 189,
      "width": 1.5,
      "smooth": false
    },
    {
      "id": "6d77a049-f537-4832-a17d-e2346c9ded34",
      "from": 162,
      "to": 224,
      "width": 1.5,
      "smooth": false
    },
    {
      "id": "917eb43e-b8d1-492f-b8f1-13a14aa1e1a5",
      "from": 224,
      "to": 165,
      "width": 1.5,
      "smooth": false
    },
    {
      "id": "017a4e1d-d0f4-43c1-823b-fa5bd7177642",
      "from": 224,
      "to": 196,
      "width": 1.5,
      "smooth": false
    },
    {
      "id": "f3256cb4-7ba4-48ae-aaaf-3b5cfd39dcd1",
      "from": 51,
      "to": 6,
      "width": 1.5,
      "smooth": false
    },
    {
      "id": "1033b183-3274-476b-93f5-e87cbd629f32",
      "from": 199,
      "to": 7,
      "width": 1.5,
      "smooth": false
    },
    {
      "id": "f04f4837-d3d9-4617-b5ff-4a5f231efbfc",
      "from": 198,
      "to": 12,
      "width": 1.5,
      "smooth": false
    },
    {
      "id": "3c31df51-b129-4cc5-8724-45dcc653be13",
      "from": 85,
      "to": 54,
      "width": 1.5,
      "smooth": false
    },
    {
      "id": "2a668a35-2564-4623-a9b7-af1699093cd7",
      "from": 60,
      "to": 15,
      "width": 1.5,
      "smooth": false
    },
    {
      "id": "3f80609f-e43e-4a25-bc98-04d0cc8d766c",
      "from": 55,
      "to": 16,
      "width": 1.5,
      "smooth": false
    }
  ],
  "settings": {
    "grid": true,
    "gridSize": 25
  }
}